{
  "_class": "group",
  "booleanOperation": -1,
  "clippingMaskMode": 0,
  "do_objectID": "86455FD1-9156-4BDD-8038-6EEACE8288BD",
  "exportOptions": {
    "_class": "exportOptions",
    "exportFormats": [
    ],
    "includedLayerIds": [
    ],
    "layerOptions": 0,
    "shouldTrim": false
  },
  "frame": {
    "_class": "rect",
    "constrainProportions": false,
    "height": 166,
    "width": 808,
    "x": 40,
    "y": 1417
  },
  "groupLayout": {
    "_class": "MSImmutableFreeformGroupLayout"
  },
  "hasClickThrough": false,
  "hasClippingMask": false,
  "isFixedToViewport": false,
  "isFlippedHorizontal": false,
  "isFlippedVertical": false,
  "isLocked": false,
  "isVisible": true,
  "layerListExpandedType": 2,
  "layers": [
    {
      "class": "text",
      "id": "027D6575-A7A8-40F9-8EE2-FB1450625EB5"
    },
    {
      "class": "symbolInstance",
      "id": "172954BE-C780-4222-912A-B46B0AFA6713"
    },
    {
      "class": "symbolInstance",
      "id": "8F581E47-ECDB-478E-98A0-E98B8C8319CE"
    },
    {
      "class": "symbolInstance",
      "id": "CB1B9045-8A18-484A-9623-31F7C952D1AA"
    },
    {
      "class": "symbolInstance",
      "id": "8A442D93-3126-472D-850F-BE13D0E5A1FD"
    },
    {
      "class": "symbolInstance",
      "id": "886E65FB-B403-4926-8C30-91FDFC109D34"
    },
    {
      "class": "symbolInstance",
      "id": "AC7C20E7-A1D6-4FCA-B3CA-665D1E174F53"
    }
  ],
  "name": "Tags",
  "nameIsFixed": true,
  "resizingConstraint": 63,
  "resizingType": 0,
  "rotation": 0,
  "shouldBreakMaskChain": false,
  "style": {
    "_class": "style",
    "blur": {
      "_class": "blur",
      "center": "{0.5, 0.5}",
      "isEnabled": false,
      "motionAngle": 0,
      "radius": 12,
      "saturation": 1,
      "type": 0
    },
    "borderOptions": {
      "_class": "borderOptions",
      "dashPattern": [
      ],
      "isEnabled": true,
      "lineCapStyle": 0,
      "lineJoinStyle": 0
    },
    "borders": [
    ],
    "colorControls": {
      "_class": "colorControls",
      "brightness": 0,
      "contrast": 1,
      "hue": 0,
      "isEnabled": false,
      "saturation": 1
    },
    "contextSettings": {
      "_class": "graphicsContextSettings",
      "blendMode": 0,
      "opacity": 1
    },
    "do_objectID": "F58D96A7-AAC0-4AF9-B536-4AF529459580",
    "endMarkerType": 0,
    "fills": [
    ],
    "innerShadows": [
    ],
    "miterLimit": 10,
    "shadows": [
    ],
    "startMarkerType": 0,
    "windingRule": 1
  }
}